[
  {
    "id": "7comment",
    "comments": [
      {
        "name": "John Anderson",
        "image": "",
        "rating": 4,
        "comment": "Excellent quality! The Logitech mouse is extremely comfortable and responsive. Perfect for long work or gaming sessions."
      },
      {
        "name": "Emily Roberts",
        "image": "",
        "rating": 5,
        "comment": "Ergonomic design and impeccable precision. This mouse exceeds all my expectations. I recommend it to everyone!"
      },
      {
        "name": "Michael Thompson",
        "image": "",
        "rating": 4,
        "comment": "The battery life is impressive. I don't have to worry about recharging all the time. Logitech hit the mark with this model!"
      },
      {
        "name": "Sophia Martinez",
        "image": "",
        "rating": 4,
        "comment": "Works perfectly on different surfaces and the wireless connection is stable and fast. Best investment I've made in peripherals."
      },
      {
        "name": "David Wilson",
        "image": "",
        "rating": 5,
        "comment": "Besides being super stylish, the mouse is very quiet and smooth. Ideal for those who work in environments that require silence. Logitech really knows how to please its customers."
      }
    ]
  }
]
